pdappend/__init__.py
pdappend/cli.py
pdappend/constants.py
pdappend/data.py
pdappend/errors.py
pdappend/gui.py
pdappend/pdappend.py
pdappend-0.2.0.dist-info/entry_points.txt
pdappend-0.2.0.dist-info/LICENSE
pdappend-0.2.0.dist-info/WHEEL
pdappend-0.2.0.dist-info/METADATA
pdappend-0.2.0.dist-info/RECORD
