Metadata-Version: 2.1
Name: pdappend
Version: 0.2.0
Summary: Append csv, xlsx, and xls files.
Home-page: https://github.com/cnpryer/pdappend
License: MIT
Author: Chris
Author-email: cnpryer@gmail.com
Requires-Python: >=3.8,<4.0
Classifier: License :: OSI Approved :: MIT License
Classifier: Programming Language :: Python :: 3
Classifier: Programming Language :: Python :: 3.10
Classifier: Programming Language :: Python :: 3.8
Classifier: Programming Language :: Python :: 3.9
Requires-Dist: click (>=8.0.4,<9.0.0)
Requires-Dist: openpyxl (>=3.0.9,<4.0.0)
Requires-Dist: pandas (>=1.4.1,<2.0.0)
Requires-Dist: python-dotenv (>=0.19.2,<0.20.0)
Requires-Dist: xlrd (>=2.0.1,<3.0.0)
Project-URL: Documentation, https://github.com/cnpryer/pdappend/wiki
Project-URL: Repository, https://github.com/cnpryer/pdappend
